[
  {
    "id": 1,
    "first_name": "Frieda",
    "last_name": "Ruffy",
    "email": "fruffy0@usda.gov",
    "gender": "Female",
    "university": "Southwest University of Science and Technology",
    "country": "China",
    "city": "Xieqiao"
  },
  {
    "id": 2,
    "first_name": "Aveline",
    "last_name": "Martinson",
    "email": "amartinson1@i2i.jp",
    "gender": "Female",
    "university": "National Aviation Univesity",
    "country": "Ukraine",
    "city": "Budy"
  },
  {
    "id": 3,
    "first_name": "Andriette",
    "last_name": "Capes",
    "email": "acapes2@edublogs.org",
    "gender": "Agender",
    "university": "Hodeidah University",
    "country": "Yemen",
    "city": "Dhī Nā‘im"
  },
  {
    "id": 4,
    "first_name": "Katine",
    "last_name": "McCandless",
    "email": "kmccandless3@cnbc.com",
    "gender": "Female",
    "university": "Toyota Technological Institute",
    "country": "Japan",
    "city": "Sumoto"
  },
  {
    "id": 5,
    "first_name": "Shea",
    "last_name": "Ravelus",
    "email": "sravelus4@sbwire.com",
    "gender": "Polygender",
    "university": "Volgograd State Academy of Physical Education",
    "country": "Russia",
    "city": "Donskoye"
  },
  {
    "id": 6,
    "first_name": "Huey",
    "last_name": "Hallatt",
    "email": "hhallatt5@amazon.de",
    "gender": "Male",
    "university": "Boston College",
    "country": "United States",
    "city": "New Haven"
  },
  {
    "id": 7,
    "first_name": "Charley",
    "last_name": "Kinworthy",
    "email": "ckinworthy6@eventbrite.com",
    "gender": "Bigender",
    "university": "Universitas Sebelas Maret",
    "country": "Indonesia",
    "city": "Krajan Puru"
  },
  {
    "id": 8,
    "first_name": "Simonette",
    "last_name": "Carding",
    "email": "scarding7@merriam-webster.com",
    "gender": "Female",
    "university": "Institut des Sciences de la Matière et du Rayonnement",
    "country": "France",
    "city": "Caen"
  },
  {
    "id": 9,
    "first_name": "Fannie",
    "last_name": "Babbs",
    "email": "fbabbs8@so-net.ne.jp",
    "gender": "Female",
    "university": "University of Saint La Salle",
    "country": "Philippines",
    "city": "Zamboanga"
  },
  {
    "id": 10,
    "first_name": "Vinson",
    "last_name": "Antalffy",
    "email": "vantalffy9@wufoo.com",
    "gender": "Male",
    "university": "Universidad Francisco de Paula Santander",
    "country": "Colombia",
    "city": "Mogotes"
  },
  {
    "id": 11,
    "first_name": "Misti",
    "last_name": "Klejna",
    "email": "mklejnaa@answers.com",
    "gender": "Agender",
    "university": "Mongolian University of Science and Technology",
    "country": "Mongolia",
    "city": "Bayasgalant"
  },
  {
    "id": 12,
    "first_name": "Georgy",
    "last_name": "Smoughton",
    "email": "gsmoughtonb@prnewswire.com",
    "gender": "Male",
    "university": "Universidad Salesiana de Bolivia",
    "country": "Bolivia",
    "city": "Vallegrande"
  },
  {
    "id": 13,
    "first_name": "Vanya",
    "last_name": "Todhunter",
    "email": "vtodhunterc@cnet.com",
    "gender": "Female",
    "university": "Universidade Federal do Maranhão",
    "country": "Brazil",
    "city": "Belford Roxo"
  },
  {
    "id": 14,
    "first_name": "Jermaine",
    "last_name": "Mathet",
    "email": "jmathetd@pbs.org",
    "gender": "Female",
    "university": "Yerevan State Medical University",
    "country": "Armenia",
    "city": "Apaga"
  },
  {
    "id": 15,
    "first_name": "Sarah",
    "last_name": "Lucken",
    "email": "sluckene@blog.com",
    "gender": "Female",
    "university": "Shandong Economic University",
    "country": "China",
    "city": "Xishan"
  },
  {
    "id": 16,
    "first_name": "Vernen",
    "last_name": "Bloggett",
    "email": "vbloggettf@de.vu",
    "gender": "Male",
    "university": "Knowledge International University",
    "country": "Saudi Arabia",
    "city": "Qal‘at Bīshah"
  },
  {
    "id": 17,
    "first_name": "Keene",
    "last_name": "Lundbeck",
    "email": "klundbeckg@who.int",
    "gender": "Male",
    "university": "Rostov State Medical University",
    "country": "Russia",
    "city": "Grecheskoye"
  },
  {
    "id": 18,
    "first_name": "Consuelo",
    "last_name": "Pawle",
    "email": "cpawleh@bluehost.com",
    "gender": "Female",
    "university": "Nanjing Normal University",
    "country": "China",
    "city": "Xingnong"
  },
  {
    "id": 19,
    "first_name": "Gardner",
    "last_name": "Lankester",
    "email": "glankesteri@infoseek.co.jp",
    "gender": "Male",
    "university": "Shanghai University of Finance and Economics",
    "country": "China",
    "city": "Yangshan"
  },
  {
    "id": 20,
    "first_name": "Pearce",
    "last_name": "Hunte",
    "email": "phuntej@flickr.com",
    "gender": "Male",
    "university": "Catholic University of Malawi",
    "country": "Malawi",
    "city": "Balaka"
  },
  {
    "id": 21,
    "first_name": "Wilma",
    "last_name": "Kubiak",
    "email": "wkubiakk@ed.gov",
    "gender": "Female",
    "university": "Universitas Brawijaya",
    "country": "Indonesia",
    "city": "Peuteuy"
  },
  {
    "id": 22,
    "first_name": "Heriberto",
    "last_name": "Burgh",
    "email": "hburghl@live.com",
    "gender": "Male",
    "university": "Universitas Muhammadiyah Sumatra Utara",
    "country": "Indonesia",
    "city": "Krajan"
  },
  {
    "id": 23,
    "first_name": "Neddy",
    "last_name": "Bushby",
    "email": "nbushbym@sciencedirect.com",
    "gender": "Male",
    "university": "Universidad Pedagógica Nacional \"Francisco Morazán\"",
    "country": "Honduras",
    "city": "La Guata"
  },
  {
    "id": 24,
    "first_name": "Shela",
    "last_name": "Meatyard",
    "email": "smeatyardn@si.edu",
    "gender": "Female",
    "university": "Universitas Muhammadiyah Sumatra Utara",
    "country": "Indonesia",
    "city": "Cibodas"
  },
  {
    "id": 25,
    "first_name": "Brnaba",
    "last_name": "Tidey",
    "email": "btideyo@canalblog.com",
    "gender": "Male",
    "university": "Njala University",
    "country": "Sierra Leone",
    "city": "Pendembu"
  },
  {
    "id": 26,
    "first_name": "Kayley",
    "last_name": "Huck",
    "email": "khuckp@jigsy.com",
    "gender": "Female",
    "university": "Universidade de São Paulo",
    "country": "Brazil",
    "city": "Rolândia"
  },
  {
    "id": 27,
    "first_name": "Kym",
    "last_name": "Benfell",
    "email": "kbenfellq@nifty.com",
    "gender": "Female",
    "university": "New Era College of Arts, Science & Technology",
    "country": "Botswana",
    "city": "Letlhakeng"
  },
  {
    "id": 28,
    "first_name": "Erek",
    "last_name": "Earle",
    "email": "eearler@dmoz.org",
    "gender": "Male",
    "university": "International College",
    "country": "United States",
    "city": "Boston"
  },
  {
    "id": 29,
    "first_name": "Elva",
    "last_name": "Gripton",
    "email": "egriptons@netscape.com",
    "gender": "Female",
    "university": "Universidade Federal Rural de Pernambuco",
    "country": "Brazil",
    "city": "Mairinque"
  },
  {
    "id": 30,
    "first_name": "Val",
    "last_name": "Farndon",
    "email": "vfarndont@livejournal.com",
    "gender": "Female",
    "university": "Technological University of Podillya",
    "country": "Ukraine",
    "city": "Arbuzynka"
  },
  {
    "id": 31,
    "first_name": "Teodor",
    "last_name": "Kristiansen",
    "email": "tkristiansenu@ed.gov",
    "gender": "Male",
    "university": "Université d'Aix-Marseille III",
    "country": "France",
    "city": "Nice"
  },
  {
    "id": 32,
    "first_name": "Blair",
    "last_name": "Pedron",
    "email": "bpedronv@gravatar.com",
    "gender": "Polygender",
    "university": "University of Lodz",
    "country": "Poland",
    "city": "Baranowo"
  },
  {
    "id": 33,
    "first_name": "Alma",
    "last_name": "Ronaghan",
    "email": "aronaghanw@flickr.com",
    "gender": "Female",
    "university": "Mid-Sweden University",
    "country": "Sweden",
    "city": "Luleå"
  },
  {
    "id": 34,
    "first_name": "Sophronia",
    "last_name": "Giroldo",
    "email": "sgiroldox@hc360.com",
    "gender": "Female",
    "university": "Universidad del País Vasco",
    "country": "Spain",
    "city": "Hospitalet De Llobregat, L'"
  },
  {
    "id": 35,
    "first_name": "Zacharie",
    "last_name": "Duinbleton",
    "email": "zduinbletony@uiuc.edu",
    "gender": "Male",
    "university": "Pedagogical University of Rzeszow",
    "country": "Poland",
    "city": "Nowa Sól"
  },
  {
    "id": 36,
    "first_name": "Jolyn",
    "last_name": "Reddick",
    "email": "jreddickz@hud.gov",
    "gender": "Female",
    "university": "Beijing University of Science and Technology",
    "country": "China",
    "city": "Jintan"
  },
  {
    "id": 37,
    "first_name": "Tandi",
    "last_name": "Beringer",
    "email": "tberinger10@mail.ru",
    "gender": "Female",
    "university": "Universidade da Beira Interior",
    "country": "Portugal",
    "city": "Barrosa"
  },
  {
    "id": 38,
    "first_name": "Ewell",
    "last_name": "Dayborne",
    "email": "edayborne11@statcounter.com",
    "gender": "Male",
    "university": "Abu Dhabi University",
    "country": "United Arab Emirates",
    "city": "Adh Dhayd"
  },
  {
    "id": 39,
    "first_name": "Pammie",
    "last_name": "Depper",
    "email": "pdepper12@i2i.jp",
    "gender": "Female",
    "university": "Universitas Sam Ratulangi",
    "country": "Indonesia",
    "city": "Fuan"
  },
  {
    "id": 40,
    "first_name": "Leelah",
    "last_name": "Keal",
    "email": "lkeal13@imgur.com",
    "gender": "Female",
    "university": "Divine Word College of Legazpi",
    "country": "Philippines",
    "city": "Balabac"
  },
  {
    "id": 41,
    "first_name": "Denyse",
    "last_name": "Ferruzzi",
    "email": "dferruzzi14@hibu.com",
    "gender": "Female",
    "university": "Ecole des Hautes Etudes Industrielles de Lille",
    "country": "France",
    "city": "Salon-de-Provence"
  },
  {
    "id": 42,
    "first_name": "Jeanna",
    "last_name": "Bauchop",
    "email": "jbauchop15@simplemachines.org",
    "gender": "Female",
    "university": "Technical University of Lublin",
    "country": "Poland",
    "city": "Kożuchów"
  },
  {
    "id": 43,
    "first_name": "Martica",
    "last_name": "Welton",
    "email": "mwelton16@istockphoto.com",
    "gender": "Female",
    "university": "Universidade do Oeste Paulista",
    "country": "Brazil",
    "city": "Guaporé"
  },
  {
    "id": 44,
    "first_name": "Prudy",
    "last_name": "Corkett",
    "email": "pcorkett17@google.com.br",
    "gender": "Female",
    "university": "Beijing Union University",
    "country": "China",
    "city": "Luoqiao"
  },
  {
    "id": 45,
    "first_name": "Noll",
    "last_name": "Maharry",
    "email": "nmaharry18@nymag.com",
    "gender": "Male",
    "university": "Northeast Forest University",
    "country": "China",
    "city": "Wuxiang"
  },
  {
    "id": 46,
    "first_name": "Bradley",
    "last_name": "Leethem",
    "email": "bleethem19@myspace.com",
    "gender": "Male",
    "university": "Nelson Mandela Metropolitan University",
    "country": "South Africa",
    "city": "Thulamahashi"
  },
  {
    "id": 47,
    "first_name": "Merci",
    "last_name": "Fenimore",
    "email": "mfenimore1a@ehow.com",
    "gender": "Female",
    "university": "Union University",
    "country": "United States",
    "city": "Van Nuys"
  },
  {
    "id": 48,
    "first_name": "Lief",
    "last_name": "Brownhall",
    "email": "lbrownhall1b@nasa.gov",
    "gender": "Male",
    "university": "Athens University of Economics and Business",
    "country": "Greece",
    "city": "Katoúna"
  },
  {
    "id": 49,
    "first_name": "Horten",
    "last_name": "Penning",
    "email": "hpenning1c@mozilla.com",
    "gender": "Male",
    "university": "Beijing University of Aeronautics and Astronautics",
    "country": "China",
    "city": "Dongfanghong"
  },
  {
    "id": 50,
    "first_name": "Cesya",
    "last_name": "Leidecker",
    "email": "cleidecker1d@mapquest.com",
    "gender": "Female",
    "university": "Universitas Mahasaraswati Denpasar",
    "country": "Indonesia",
    "city": "Lengkongsari"
  },
  {
    "id": 51,
    "first_name": "Bertrand",
    "last_name": "Artis",
    "email": "bartis1e@omniture.com",
    "gender": "Male",
    "university": "Cape Peninsula University of Technology",
    "country": "South Africa",
    "city": "Greytown"
  },
  {
    "id": 52,
    "first_name": "Henka",
    "last_name": "Crosfeld",
    "email": "hcrosfeld1f@go.com",
    "gender": "Female",
    "university": "Universidad Andina del Cusco",
    "country": "Peru",
    "city": "Checacupe"
  },
  {
    "id": 53,
    "first_name": "Alameda",
    "last_name": "Dommersen",
    "email": "adommersen1g@state.tx.us",
    "gender": "Polygender",
    "university": "Beijing Union University",
    "country": "China",
    "city": "Qiting"
  },
  {
    "id": 54,
    "first_name": "Catlaina",
    "last_name": "Lars",
    "email": "clars1h@symantec.com",
    "gender": "Female",
    "university": "University of Pardubice",
    "country": "Czech Republic",
    "city": "Bílina Kyselka"
  },
  {
    "id": 55,
    "first_name": "Clarinda",
    "last_name": "Audas",
    "email": "caudas1i@fema.gov",
    "gender": "Non-binary",
    "university": "Chinhoyi University of Technology",
    "country": "Zimbabwe",
    "city": "Headlands"
  },
  {
    "id": 56,
    "first_name": "Emmerich",
    "last_name": "Kellog",
    "email": "ekellog1j@reference.com",
    "gender": "Non-binary",
    "university": "Zhengzhou Grain University",
    "country": "China",
    "city": "Wanquan"
  },
  {
    "id": 57,
    "first_name": "Kerk",
    "last_name": "Headon",
    "email": "kheadon1k@samsung.com",
    "gender": "Male",
    "university": "Chongqing Telecommunication College",
    "country": "China",
    "city": "Taoling"
  },
  {
    "id": 58,
    "first_name": "Bridgette",
    "last_name": "Pipworth",
    "email": "bpipworth1l@china.com.cn",
    "gender": "Agender",
    "university": "Universidad Nacional Federico Villarreal",
    "country": "Peru",
    "city": "Tembladera"
  },
  {
    "id": 59,
    "first_name": "Kittie",
    "last_name": "Zelland",
    "email": "kzelland1m@psu.edu",
    "gender": "Female",
    "university": "University of Fine Arts Belgrade",
    "country": "Serbia",
    "city": "Jagodina"
  },
  {
    "id": 60,
    "first_name": "Elroy",
    "last_name": "Swaile",
    "email": "eswaile1n@geocities.com",
    "gender": "Male",
    "university": "Universidad José Cecilio del Valle",
    "country": "Honduras",
    "city": "Aramecina"
  },
  {
    "id": 61,
    "first_name": "Ezra",
    "last_name": "McAnalley",
    "email": "emcanalley1o@eventbrite.com",
    "gender": "Male",
    "university": "Bukkyo University",
    "country": "Japan",
    "city": "Kasugai"
  },
  {
    "id": 62,
    "first_name": "Vikky",
    "last_name": "Brosio",
    "email": "vbrosio1p@spotify.com",
    "gender": "Polygender",
    "university": "Universitas 17 Agustus 1945 Jakarta",
    "country": "Indonesia",
    "city": "Dlemer"
  },
  {
    "id": 63,
    "first_name": "Celle",
    "last_name": "Partner",
    "email": "cpartner1q@myspace.com",
    "gender": "Female",
    "university": "Alhosn University",
    "country": "United Arab Emirates",
    "city": "Dubai"
  },
  {
    "id": 64,
    "first_name": "Hanni",
    "last_name": "Dewsnap",
    "email": "hdewsnap1r@sakura.ne.jp",
    "gender": "Female",
    "university": "Islamic Azad University, Gorgan",
    "country": "Iran",
    "city": "Behābād"
  },
  {
    "id": 65,
    "first_name": "Silvain",
    "last_name": "Andrea",
    "email": "sandrea1s@statcounter.com",
    "gender": "Polygender",
    "university": "Harbin Medical University",
    "country": "China",
    "city": "Touzao"
  },
  {
    "id": 66,
    "first_name": "Skip",
    "last_name": "Allinson",
    "email": "sallinson1t@geocities.com",
    "gender": "Male",
    "university": "Saratov State Academy of Law",
    "country": "Russia",
    "city": "Kantyshevo"
  },
  {
    "id": 67,
    "first_name": "Ermin",
    "last_name": "Jefferd",
    "email": "ejefferd1u@webs.com",
    "gender": "Male",
    "university": "University of Bergamo",
    "country": "Italy",
    "city": "Napoli"
  },
  {
    "id": 68,
    "first_name": "Marcelle",
    "last_name": "Shitliff",
    "email": "mshitliff1v@statcounter.com",
    "gender": "Non-binary",
    "university": "St. Petersburg State Theatre Arts Academy",
    "country": "Russia",
    "city": "Gorbunki"
  },
  {
    "id": 69,
    "first_name": "Zara",
    "last_name": "Smitham",
    "email": "zsmitham1w@php.net",
    "gender": "Female",
    "university": "Music Academy \"Fryderyk Chopin\" in Warszaw",
    "country": "Poland",
    "city": "Śródmieście"
  },
  {
    "id": 70,
    "first_name": "Glenna",
    "last_name": "Wiltsher",
    "email": "gwiltsher1x@studiopress.com",
    "gender": "Female",
    "university": "International University of Southern Europe",
    "country": "Spain",
    "city": "Valencia"
  },
  {
    "id": 71,
    "first_name": "Tarrance",
    "last_name": "McGeaney",
    "email": "tmcgeaney1y@deliciousdays.com",
    "gender": "Male",
    "university": "Universidad Autónoma de la Laguna",
    "country": "Mexico",
    "city": "San Antonio"
  },
  {
    "id": 72,
    "first_name": "Mary",
    "last_name": "Wegener",
    "email": "mwegener1z@nps.gov",
    "gender": "Female",
    "university": "Universidad Tecnológica de Honduras",
    "country": "Honduras",
    "city": "Guacamaya"
  },
  {
    "id": 73,
    "first_name": "Jermain",
    "last_name": "Louder",
    "email": "jlouder20@wufoo.com",
    "gender": "Male",
    "university": "Politeknik Pos Indonesia",
    "country": "Indonesia",
    "city": "Krajan Satu"
  },
  {
    "id": 74,
    "first_name": "Candis",
    "last_name": "Betham",
    "email": "cbetham21@jimdo.com",
    "gender": "Female",
    "university": "Danang College Of Technology",
    "country": "Vietnam",
    "city": "Thanh Nê"
  },
  {
    "id": 75,
    "first_name": "Donica",
    "last_name": "Tregona",
    "email": "dtregona22@pinterest.com",
    "gender": "Female",
    "university": "Huaihua Medical College",
    "country": "China",
    "city": "Siquanpu"
  },
  {
    "id": 76,
    "first_name": "Morton",
    "last_name": "Ingram",
    "email": "mingram23@google.co.uk",
    "gender": "Male",
    "university": "Universidade Metodista de Angola",
    "country": "Angola",
    "city": "Soio"
  },
  {
    "id": 77,
    "first_name": "Jareb",
    "last_name": "Bellinger",
    "email": "jbellinger24@ftc.gov",
    "gender": "Male",
    "university": "Lumbini Buddhist University",
    "country": "Nepal",
    "city": "Gulariyā"
  },
  {
    "id": 78,
    "first_name": "Jarib",
    "last_name": "Craisford",
    "email": "jcraisford25@tmall.com",
    "gender": "Male",
    "university": "Instituto Politécnico do Cávado e do Ave",
    "country": "Portugal",
    "city": "Senhor da Serra"
  },
  {
    "id": 79,
    "first_name": "Granville",
    "last_name": "Spratling",
    "email": "gspratling26@chronoengine.com",
    "gender": "Male",
    "university": "Universidade de Tras-os-Montes e Alto Douro",
    "country": "Portugal",
    "city": "Amieiro"
  },
  {
    "id": 80,
    "first_name": "Garreth",
    "last_name": "Rodmell",
    "email": "grodmell27@cloudflare.com",
    "gender": "Bigender",
    "university": "Xiamen University",
    "country": "China",
    "city": "Zhuyang"
  },
  {
    "id": 81,
    "first_name": "Oriana",
    "last_name": "Gallaher",
    "email": "ogallaher28@sakura.ne.jp",
    "gender": "Female",
    "university": "Shanxi Normal University",
    "country": "China",
    "city": "Fuji"
  },
  {
    "id": 82,
    "first_name": "Claire",
    "last_name": "Tennant",
    "email": "ctennant29@e-recht24.de",
    "gender": "Male",
    "university": "Universidad Tecnológica Centroamericana",
    "country": "Honduras",
    "city": "Sulaco"
  },
  {
    "id": 83,
    "first_name": "Lowell",
    "last_name": "Naldrett",
    "email": "lnaldrett2a@storify.com",
    "gender": "Male",
    "university": "Universitas Merdeka Madiun",
    "country": "Indonesia",
    "city": "Jarada"
  },
  {
    "id": 84,
    "first_name": "Lyndsey",
    "last_name": "Crevy",
    "email": "lcrevy2b@google.com.hk",
    "gender": "Female",
    "university": "Tarlac State University",
    "country": "Philippines",
    "city": "Lamak"
  },
  {
    "id": 85,
    "first_name": "Delmer",
    "last_name": "Chell",
    "email": "dchell2c@mapy.cz",
    "gender": "Male",
    "university": "City University Programs in Bulgaria ",
    "country": "Bulgaria",
    "city": "Rila"
  },
  {
    "id": 86,
    "first_name": "Cully",
    "last_name": "Poolton",
    "email": "cpoolton2d@blogger.com",
    "gender": "Male",
    "university": "Hogeschool Inholland",
    "country": "Netherlands",
    "city": "Venlo"
  },
  {
    "id": 87,
    "first_name": "Brenn",
    "last_name": "Beminster",
    "email": "bbeminster2e@amazon.co.uk",
    "gender": "Female",
    "university": "National University of Food Technologies",
    "country": "Ukraine",
    "city": "Tynne"
  },
  {
    "id": 88,
    "first_name": "Hanna",
    "last_name": "Speck",
    "email": "hspeck2f@sohu.com",
    "gender": "Female",
    "university": "National University of Uzbekistan",
    "country": "Uzbekistan",
    "city": "Koson Shahri"
  },
  {
    "id": 89,
    "first_name": "Jackqueline",
    "last_name": "Orgill",
    "email": "jorgill2g@google.pl",
    "gender": "Female",
    "university": "University of Opole",
    "country": "Poland",
    "city": "Radzanów"
  },
  {
    "id": 90,
    "first_name": "Trixie",
    "last_name": "Mucci",
    "email": "tmucci2h@pbs.org",
    "gender": "Bigender",
    "university": "Universitas Andalas",
    "country": "Indonesia",
    "city": "Rancaerang"
  },
  {
    "id": 91,
    "first_name": "Leonanie",
    "last_name": "Burgess",
    "email": "lburgess2i@sphinn.com",
    "gender": "Female",
    "university": "RMIT International University Vietnam",
    "country": "Vietnam",
    "city": "Vân Canh"
  },
  {
    "id": 92,
    "first_name": "Antonio",
    "last_name": "Minchi",
    "email": "aminchi2j@harvard.edu",
    "gender": "Male",
    "university": "Universitas Madura",
    "country": "Indonesia",
    "city": "Sempu"
  },
  {
    "id": 93,
    "first_name": "Fernando",
    "last_name": "Starie",
    "email": "fstarie2k@sun.com",
    "gender": "Male",
    "university": "Universidad Nacional Experimental Politécnica \"Antonio José de Sucre\"",
    "country": "Venezuela",
    "city": "Ciudad Bolívar"
  },
  {
    "id": 94,
    "first_name": "Averyl",
    "last_name": "Ansley",
    "email": "aansley2l@storify.com",
    "gender": "Female",
    "university": "Christchurch Polytechnic Institute of Technology",
    "country": "New Zealand",
    "city": "Bluff"
  },
  {
    "id": 95,
    "first_name": "Cele",
    "last_name": "Mattisson",
    "email": "cmattisson2m@addtoany.com",
    "gender": "Female",
    "university": "Universidade de Santa Cruz do Sul",
    "country": "Brazil",
    "city": "Pinheiral"
  },
  {
    "id": 96,
    "first_name": "Alie",
    "last_name": "Plumbridge",
    "email": "aplumbridge2n@state.tx.us",
    "gender": "Female",
    "university": "National University of Laos",
    "country": "Laos",
    "city": "Xam Nua"
  },
  {
    "id": 97,
    "first_name": "Ailsun",
    "last_name": "Casely",
    "email": "acasely2o@hao123.com",
    "gender": "Female",
    "university": "Pontificia Universidad Javeriana",
    "country": "Colombia",
    "city": "Chimichagua"
  },
  {
    "id": 98,
    "first_name": "Letizia",
    "last_name": "Guyer",
    "email": "lguyer2p@theatlantic.com",
    "gender": "Female",
    "university": "Universidade Catolica Portuguesa",
    "country": "Portugal",
    "city": "Quinta"
  },
  {
    "id": 99,
    "first_name": "Nisse",
    "last_name": "Berggren",
    "email": "nberggren2q@nba.com",
    "gender": "Female",
    "university": "Chongqing Technology and Business University",
    "country": "China",
    "city": "Liuzhuang"
  },
  {
    "id": 100,
    "first_name": "Lenka",
    "last_name": "Iwanowski",
    "email": "liwanowski2r@theguardian.com",
    "gender": "Female",
    "university": "Yunnan Normal University",
    "country": "China",
    "city": "Yangzhuang"
  },
  {
    "id": 101,
    "first_name": "Annice",
    "last_name": "Sleite",
    "email": "asleite2s@apache.org",
    "gender": "Female",
    "university": "Shanghai Business School",
    "country": "China",
    "city": "Yunji"
  },
  {
    "id": 102,
    "first_name": "Antin",
    "last_name": "Sey",
    "email": "asey2t@google.com",
    "gender": "Male",
    "university": "Universidade do Minho",
    "country": "Portugal",
    "city": "Feteira Grande"
  },
  {
    "id": 103,
    "first_name": "Bevan",
    "last_name": "Hanton",
    "email": "bhanton2u@tiny.cc",
    "gender": "Male",
    "university": "Dalian Polytechnic University",
    "country": "China",
    "city": "Shanxia"
  },
  {
    "id": 104,
    "first_name": "Sheena",
    "last_name": "Rumble",
    "email": "srumble2v@google.com.au",
    "gender": "Female",
    "university": "Urbana University",
    "country": "United States",
    "city": "Boca Raton"
  },
  {
    "id": 105,
    "first_name": "Dede",
    "last_name": "Blasius",
    "email": "dblasius2w@chicagotribune.com",
    "gender": "Female",
    "university": "European University",
    "country": "Serbia",
    "city": "Gardinovci"
  },
  {
    "id": 106,
    "first_name": "Thornton",
    "last_name": "Barrowcliff",
    "email": "tbarrowcliff2x@freewebs.com",
    "gender": "Male",
    "university": "Universidad de las Américas (ULAM)",
    "country": "Nicaragua",
    "city": "La Jicaral"
  },
  {
    "id": 107,
    "first_name": "Petey",
    "last_name": "Philipart",
    "email": "pphilipart2y@hibu.com",
    "gender": "Male",
    "university": "Instituto Superior de Assistentes e Intérpretes",
    "country": "Portugal",
    "city": "Casa Nova"
  },
  {
    "id": 108,
    "first_name": "Sanderson",
    "last_name": "Noriega",
    "email": "snoriega2z@huffingtonpost.com",
    "gender": "Male",
    "university": "Zuyd University",
    "country": "Netherlands",
    "city": "Tilburg"
  },
  {
    "id": 109,
    "first_name": "Wilfrid",
    "last_name": "Aksell",
    "email": "waksell30@answers.com",
    "gender": "Male",
    "university": "Universidade Portucalense Infante D. Henrique",
    "country": "Portugal",
    "city": "Mozelos"
  },
  {
    "id": 110,
    "first_name": "Brunhilda",
    "last_name": "Benbrick",
    "email": "bbenbrick31@altervista.org",
    "gender": "Female",
    "university": "Health sciences University of Mongolia",
    "country": "Mongolia",
    "city": "Arvayheer"
  },
  {
    "id": 111,
    "first_name": "Graig",
    "last_name": "McCurtin",
    "email": "gmccurtin32@amazon.com",
    "gender": "Male",
    "university": "KDI School of Public Policy and Management",
    "country": "South Korea",
    "city": "Hanam"
  },
  {
    "id": 112,
    "first_name": "Tomasine",
    "last_name": "McCluskey",
    "email": "tmccluskey33@admin.ch",
    "gender": "Female",
    "university": "Universidad de Lambayeque",
    "country": "Peru",
    "city": "Quinocay"
  },
  {
    "id": 113,
    "first_name": "Reyna",
    "last_name": "Parcell",
    "email": "rparcell34@amazon.com",
    "gender": "Female",
    "university": "Semey State Medical University",
    "country": "Kazakhstan",
    "city": "Aktau"
  },
  {
    "id": 114,
    "first_name": "Maryanne",
    "last_name": "Francey",
    "email": "mfrancey35@ed.gov",
    "gender": "Female",
    "university": "Polonia University in Czêstochowa",
    "country": "Poland",
    "city": "Wyszków"
  },
  {
    "id": 115,
    "first_name": "Franklyn",
    "last_name": "Cooke",
    "email": "fcooke36@webeden.co.uk",
    "gender": "Male",
    "university": "2nd Military Medical University",
    "country": "China",
    "city": "Nianba"
  },
  {
    "id": 116,
    "first_name": "Price",
    "last_name": "Summerrell",
    "email": "psummerrell37@webeden.co.uk",
    "gender": "Male",
    "university": "Institute of Management and Economy",
    "country": "Russia",
    "city": "Spasskoye-Lutovinovo"
  },
  {
    "id": 117,
    "first_name": "Toddie",
    "last_name": "Olman",
    "email": "tolman38@arstechnica.com",
    "gender": "Male",
    "university": "Universidad Metropolitana de Honduras",
    "country": "Honduras",
    "city": "Santa Rosa de Copán"
  },
  {
    "id": 118,
    "first_name": "Newton",
    "last_name": "Banasik",
    "email": "nbanasik39@oakley.com",
    "gender": "Male",
    "university": "Institut Teknologi Sepuluh Nopember",
    "country": "Indonesia",
    "city": "Ngurenrejo"
  },
  {
    "id": 119,
    "first_name": "Cedric",
    "last_name": "Tiery",
    "email": "ctiery3a@jimdo.com",
    "gender": "Male",
    "university": "Universidade Vale do Rio Doce",
    "country": "Brazil",
    "city": "Varjota"
  },
  {
    "id": 120,
    "first_name": "Linell",
    "last_name": "Gidney",
    "email": "lgidney3b@example.com",
    "gender": "Female",
    "university": "Southwest Petroleum University",
    "country": "China",
    "city": "Baoshan"
  },
  {
    "id": 121,
    "first_name": "Delbert",
    "last_name": "Goulden",
    "email": "dgoulden3c@cpanel.net",
    "gender": "Male",
    "university": "Jiangxi University of Finance and Economics",
    "country": "China",
    "city": "Xibu"
  },
  {
    "id": 122,
    "first_name": "Gunter",
    "last_name": "Tatershall",
    "email": "gtatershall3d@oakley.com",
    "gender": "Male",
    "university": "Cheljabinsk State Institute of Teacher Training",
    "country": "Russia",
    "city": "Dubovka"
  },
  {
    "id": 123,
    "first_name": "Myer",
    "last_name": "Necrews",
    "email": "mnecrews3e@deliciousdays.com",
    "gender": "Male",
    "university": "Jilin University of Technology",
    "country": "China",
    "city": "Nanhuang"
  },
  {
    "id": 124,
    "first_name": "Ursala",
    "last_name": "Gilstoun",
    "email": "ugilstoun3f@abc.net.au",
    "gender": "Non-binary",
    "university": "Ecole Nationale Supérieure de l'Aéronautique et de l'Espace",
    "country": "France",
    "city": "Angers"
  },
  {
    "id": 125,
    "first_name": "Haven",
    "last_name": "Meak",
    "email": "hmeak3g@naver.com",
    "gender": "Male",
    "university": "Hellenic Army Academy",
    "country": "Greece",
    "city": "Polykárpi"
  },
  {
    "id": 126,
    "first_name": "Seumas",
    "last_name": "Newlands",
    "email": "snewlands3h@sakura.ne.jp",
    "gender": "Male",
    "university": "National Technical University of Athens",
    "country": "Greece",
    "city": "Panaitólion"
  },
  {
    "id": 127,
    "first_name": "Kathie",
    "last_name": "Moberley",
    "email": "kmoberley3i@wiley.com",
    "gender": "Genderfluid",
    "university": "Manuel L. Quezon University",
    "country": "Philippines",
    "city": "Patrocinio"
  },
  {
    "id": 128,
    "first_name": "Kellsie",
    "last_name": "Sullivan",
    "email": "ksullivan3j@linkedin.com",
    "gender": "Non-binary",
    "university": "Universidade Eduardo Mondlane",
    "country": "Mozambique",
    "city": "Montepuez"
  },
  {
    "id": 129,
    "first_name": "Salvatore",
    "last_name": "Biernat",
    "email": "sbiernat3k@mac.com",
    "gender": "Polygender",
    "university": "Józef Tyszkiewicz College of Business and Computer Science in Bielsko-Biala",
    "country": "Poland",
    "city": "Krzęcin"
  },
  {
    "id": 130,
    "first_name": "Deck",
    "last_name": "Edsell",
    "email": "dedsell3l@cnet.com",
    "gender": "Male",
    "university": "West Visayas State University",
    "country": "Philippines",
    "city": "Valencia"
  },
  {
    "id": 131,
    "first_name": "Emogene",
    "last_name": "Tattershall",
    "email": "etattershall3m@sitemeter.com",
    "gender": "Female",
    "university": "Universitas Dian Nuswantoro",
    "country": "Indonesia",
    "city": "Pakis"
  },
  {
    "id": 132,
    "first_name": "Roger",
    "last_name": "Rosendale",
    "email": "rrosendale3n@weather.com",
    "gender": "Male",
    "university": "Tokushima University",
    "country": "Japan",
    "city": "Nagahama"
  },
  {
    "id": 133,
    "first_name": "Pierette",
    "last_name": "Apdell",
    "email": "papdell3o@mysql.com",
    "gender": "Female",
    "university": "Université de Reims Champagne-Ardenne",
    "country": "France",
    "city": "Suresnes"
  },
  {
    "id": 134,
    "first_name": "Nicolas",
    "last_name": "Sherrott",
    "email": "nsherrott3p@home.pl",
    "gender": "Male",
    "university": "Estonian University of Life Sciences",
    "country": "Estonia",
    "city": "Narva-Jõesuu"
  },
  {
    "id": 135,
    "first_name": "Clement",
    "last_name": "O'Kelly",
    "email": "cokelly3q@taobao.com",
    "gender": "Male",
    "university": "Hebei Academy of Fine Art",
    "country": "China",
    "city": "Maoyang"
  },
  {
    "id": 136,
    "first_name": "Aila",
    "last_name": "Uebel",
    "email": "auebel3r@skype.com",
    "gender": "Non-binary",
    "university": "Southwest Forestry University",
    "country": "China",
    "city": "Huaidao"
  },
  {
    "id": 137,
    "first_name": "Rosene",
    "last_name": "Keedwell",
    "email": "rkeedwell3s@tuttocitta.it",
    "gender": "Female",
    "university": "Yangzhou University",
    "country": "China",
    "city": "Bayan Tuohai"
  },
  {
    "id": 138,
    "first_name": "Daphne",
    "last_name": "MacAne",
    "email": "dmacane3t@cnn.com",
    "gender": "Female",
    "university": "Kampala International University",
    "country": "Uganda",
    "city": "Kayunga"
  },
  {
    "id": 139,
    "first_name": "Eugine",
    "last_name": "Itzkov",
    "email": "eitzkov3u@qq.com",
    "gender": "Female",
    "university": "Groupe Sup de Co Montpellier",
    "country": "France",
    "city": "Caen"
  },
  {
    "id": 140,
    "first_name": "Thorpe",
    "last_name": "Guerri",
    "email": "tguerri3v@pinterest.com",
    "gender": "Male",
    "university": "University of Mohaghegh",
    "country": "Iran",
    "city": "Bastak"
  },
  {
    "id": 141,
    "first_name": "Cairistiona",
    "last_name": "Norcock",
    "email": "cnorcock3w@ezinearticles.com",
    "gender": "Female",
    "university": "University of New Caledonia",
    "country": "New Caledonia",
    "city": "Nouméa"
  },
  {
    "id": 142,
    "first_name": "Byrom",
    "last_name": "Borzone",
    "email": "bborzone3x@oaic.gov.au",
    "gender": "Male",
    "university": "National University of Samoa",
    "country": "Samoa",
    "city": "Faleula"
  },
  {
    "id": 143,
    "first_name": "Hube",
    "last_name": "Bartolomeo",
    "email": "hbartolomeo3y@aboutads.info",
    "gender": "Male",
    "university": "Universitas Haluoleo",
    "country": "Indonesia",
    "city": "Mislak"
  },
  {
    "id": 144,
    "first_name": "Kiele",
    "last_name": "Lammenga",
    "email": "klammenga3z@bandcamp.com",
    "gender": "Female",
    "university": "Universidade Católica de Pernambuco",
    "country": "Brazil",
    "city": "Elias Fausto"
  },
  {
    "id": 145,
    "first_name": "Isadore",
    "last_name": "Rawson",
    "email": "irawson40@gizmodo.com",
    "gender": "Male",
    "university": "University of the City of Manila",
    "country": "Philippines",
    "city": "Pagsanahan Norte"
  },
  {
    "id": 146,
    "first_name": "Garald",
    "last_name": "Rupert",
    "email": "grupert41@amazon.de",
    "gender": "Agender",
    "university": "Taizhou College",
    "country": "China",
    "city": "Tanghu"
  },
  {
    "id": 147,
    "first_name": "Cirillo",
    "last_name": "Ballinger",
    "email": "cballinger42@meetup.com",
    "gender": "Male",
    "university": "Universidad Nacional Experimental del Táchira",
    "country": "Venezuela",
    "city": "Capacho Nuevo"
  },
  {
    "id": 148,
    "first_name": "Kerr",
    "last_name": "Klas",
    "email": "kklas43@seesaa.net",
    "gender": "Male",
    "university": "Escola Superior de Artes e Design",
    "country": "Portugal",
    "city": "Carreira"
  },
  {
    "id": 149,
    "first_name": "Barclay",
    "last_name": "de Voiels",
    "email": "bdevoiels44@columbia.edu",
    "gender": "Male",
    "university": "Herzen State Pedagogical University of Russia",
    "country": "Russia",
    "city": "Novotroitsk"
  },
  {
    "id": 150,
    "first_name": "Sadella",
    "last_name": "Gunthorp",
    "email": "sgunthorp45@comsenz.com",
    "gender": "Female",
    "university": "Mendel University of Agriculture and Forestry",
    "country": "Czech Republic",
    "city": "Žleby"
  },
  {
    "id": 151,
    "first_name": "Lauren",
    "last_name": "Presdie",
    "email": "lpresdie46@cornell.edu",
    "gender": "Male",
    "university": "Universidade Federal de Sergipe",
    "country": "Brazil",
    "city": "São Borja"
  },
  {
    "id": 152,
    "first_name": "Jeanna",
    "last_name": "Eykelbosch",
    "email": "jeykelbosch47@canalblog.com",
    "gender": "Female",
    "university": "Shandong University",
    "country": "China",
    "city": "Jiefangyan"
  },
  {
    "id": 153,
    "first_name": "Alphonse",
    "last_name": "Bruni",
    "email": "abruni48@linkedin.com",
    "gender": "Male",
    "university": "University of Technical Education Ho Chi Minh City",
    "country": "Vietnam",
    "city": "Thị Trấn Thất Khê"
  },
  {
    "id": 154,
    "first_name": "Gustie",
    "last_name": "Inderwick",
    "email": "ginderwick49@desdev.cn",
    "gender": "Female",
    "university": "Guangxi University",
    "country": "China",
    "city": "Qiaolin"
  },
  {
    "id": 155,
    "first_name": "Bobbie",
    "last_name": "Di Matteo",
    "email": "bdimatteo4a@rediff.com",
    "gender": "Male",
    "university": "Universidad del Norte",
    "country": "Colombia",
    "city": "Santa Rosa de Cabal"
  },
  {
    "id": 156,
    "first_name": "Barbee",
    "last_name": "Clearley",
    "email": "bclearley4b@ovh.net",
    "gender": "Female",
    "university": "Université de Corse Pascal Paoli",
    "country": "France",
    "city": "Puteaux"
  },
  {
    "id": 157,
    "first_name": "Petronia",
    "last_name": "Counihan",
    "email": "pcounihan4c@networksolutions.com",
    "gender": "Female",
    "university": "Nanjing Institute of Meteorology",
    "country": "China",
    "city": "Changgai"
  },
  {
    "id": 158,
    "first_name": "Cordy",
    "last_name": "Mance",
    "email": "cmance4d@163.com",
    "gender": "Male",
    "university": "Zhanjiang Ocean University",
    "country": "China",
    "city": "Xing’an"
  },
  {
    "id": 159,
    "first_name": "Ebeneser",
    "last_name": "Robison",
    "email": "erobison4e@mysql.com",
    "gender": "Male",
    "university": "Aegean University",
    "country": "Greece",
    "city": "Efkarpía"
  },
  {
    "id": 160,
    "first_name": "Alma",
    "last_name": "Bourdice",
    "email": "abourdice4f@usnews.com",
    "gender": "Non-binary",
    "university": "Vitebsk State Technological University",
    "country": "Belarus",
    "city": "Skidal’"
  },
  {
    "id": 161,
    "first_name": "Hilde",
    "last_name": "Guirard",
    "email": "hguirard4g@ucla.edu",
    "gender": "Female",
    "university": "Balqa Applied University",
    "country": "Jordan",
    "city": "Al Quwaysimah"
  },
  {
    "id": 162,
    "first_name": "Ashla",
    "last_name": "Rickeard",
    "email": "arickeard4h@hexun.com",
    "gender": "Female",
    "university": "St. Joseph Group of Institutes",
    "country": "Tanzania",
    "city": "Igurubi"
  },
  {
    "id": 163,
    "first_name": "Orville",
    "last_name": "Eastmond",
    "email": "oeastmond4i@blinklist.com",
    "gender": "Male",
    "university": "Universidad de la República",
    "country": "Uruguay",
    "city": "Santa Bernardina"
  },
  {
    "id": 164,
    "first_name": "Kenyon",
    "last_name": "Richardet",
    "email": "krichardet4j@shinystat.com",
    "gender": "Male",
    "university": "Universitas Muhammadiyah Mataram",
    "country": "Indonesia",
    "city": "Kubang"
  },
  {
    "id": 165,
    "first_name": "Niall",
    "last_name": "Yosselevitch",
    "email": "nyosselevitch4k@furl.net",
    "gender": "Male",
    "university": "Shanghai Customs College",
    "country": "China",
    "city": "Hairag"
  },
  {
    "id": 166,
    "first_name": "Donalt",
    "last_name": "Fellona",
    "email": "dfellona4l@netlog.com",
    "gender": "Male",
    "university": "Universitas Wijaya Kusuma Purwokerto",
    "country": "Indonesia",
    "city": "Gayamdesa"
  },
  {
    "id": 167,
    "first_name": "Eleen",
    "last_name": "Abrahim",
    "email": "eabrahim4m@barnesandnoble.com",
    "gender": "Female",
    "university": "National Metallurgical Academy of Ukraine",
    "country": "Ukraine",
    "city": "Dzvinogrud"
  },
  {
    "id": 168,
    "first_name": "Oran",
    "last_name": "Gaines",
    "email": "ogaines4n@usa.gov",
    "gender": "Male",
    "university": "Zanjan University",
    "country": "Iran",
    "city": "Solţānābād"
  },
  {
    "id": 169,
    "first_name": "Dur",
    "last_name": "Dallosso",
    "email": "ddallosso4o@ucla.edu",
    "gender": "Male",
    "university": "Jiangxi Agricultural University",
    "country": "China",
    "city": "Tushi"
  },
  {
    "id": 170,
    "first_name": "Marina",
    "last_name": "Woolaghan",
    "email": "mwoolaghan4p@oakley.com",
    "gender": "Female",
    "university": "Belgorod State University",
    "country": "Russia",
    "city": "Sergiyev Posad"
  },
  {
    "id": 171,
    "first_name": "Darci",
    "last_name": "Creasy",
    "email": "dcreasy4q@opera.com",
    "gender": "Female",
    "university": "Universidad Autónoma de Madrid",
    "country": "Spain",
    "city": "Santander"
  },
  {
    "id": 172,
    "first_name": "Liliane",
    "last_name": "Jacqueminot",
    "email": "ljacqueminot4r@alexa.com",
    "gender": "Female",
    "university": "Guizhou University",
    "country": "China",
    "city": "Xinji"
  },
  {
    "id": 173,
    "first_name": "Lorilyn",
    "last_name": "Andrin",
    "email": "landrin4s@opensource.org",
    "gender": "Female",
    "university": "Western Galilee College",
    "country": "Israel",
    "city": "Kafr Kannā"
  },
  {
    "id": 174,
    "first_name": "Charlene",
    "last_name": "Tildesley",
    "email": "ctildesley4t@artisteer.com",
    "gender": "Bigender",
    "university": "Alkharj University",
    "country": "Saudi Arabia",
    "city": "Abha"
  },
  {
    "id": 175,
    "first_name": "Garik",
    "last_name": "Dunsmore",
    "email": "gdunsmore4u@columbia.edu",
    "gender": "Genderfluid",
    "university": "National Medical University O.O. Bogomolets",
    "country": "Ukraine",
    "city": "Klavdiyevo-Tarasove"
  },
  {
    "id": 176,
    "first_name": "Myrah",
    "last_name": "Becke",
    "email": "mbecke4v@t-online.de",
    "gender": "Female",
    "university": "Instituto Politécnico do Cávado e do Ave",
    "country": "Portugal",
    "city": "Lamego"
  },
  {
    "id": 177,
    "first_name": "Wylie",
    "last_name": "Adamiec",
    "email": "wadamiec4w@upenn.edu",
    "gender": "Male",
    "university": "Yerevan State Medical University",
    "country": "Armenia",
    "city": "Geghanist"
  },
  {
    "id": 178,
    "first_name": "Haroun",
    "last_name": "Laydel",
    "email": "hlaydel4x@netlog.com",
    "gender": "Male",
    "university": "Universidad Nacional del Sur",
    "country": "Argentina",
    "city": "Presidencia Roque Sáenz Peña"
  },
  {
    "id": 179,
    "first_name": "Carrol",
    "last_name": "Dobeson",
    "email": "cdobeson4y@narod.ru",
    "gender": "Male",
    "university": "Peking University",
    "country": "China",
    "city": "Pengwan"
  },
  {
    "id": 180,
    "first_name": "Ruttger",
    "last_name": "Issac",
    "email": "rissac4z@sciencedaily.com",
    "gender": "Male",
    "university": "Universitas Krisnadwipayana",
    "country": "Indonesia",
    "city": "Penitik"
  },
  {
    "id": 181,
    "first_name": "Dulci",
    "last_name": "Gartland",
    "email": "dgartland50@symantec.com",
    "gender": "Female",
    "university": "Heilongjiang Commercial University",
    "country": "China",
    "city": "Xinhua"
  },
  {
    "id": 182,
    "first_name": "Svend",
    "last_name": "Arnaudot",
    "email": "sarnaudot51@unblog.fr",
    "gender": "Male",
    "university": "Universidad San Martin de Porres",
    "country": "Peru",
    "city": "Aucayacu"
  },
  {
    "id": 183,
    "first_name": "Novelia",
    "last_name": "Tudball",
    "email": "ntudball52@rediff.com",
    "gender": "Female",
    "university": "Ufa State Petroleum Technological University",
    "country": "Russia",
    "city": "Novosemeykino"
  },
  {
    "id": 184,
    "first_name": "Chantalle",
    "last_name": "Lucio",
    "email": "clucio53@skype.com",
    "gender": "Bigender",
    "university": "Shanxi Agricultural University",
    "country": "China",
    "city": "Guanyinge"
  },
  {
    "id": 185,
    "first_name": "Sisely",
    "last_name": "Leggon",
    "email": "sleggon54@1und1.de",
    "gender": "Polygender",
    "university": "Universitas Dian Nuswantoro",
    "country": "Indonesia",
    "city": "Bojonegoro"
  },
  {
    "id": 186,
    "first_name": "Lyndsey",
    "last_name": "Carnalan",
    "email": "lcarnalan55@google.nl",
    "gender": "Female",
    "university": "Ferris State University",
    "country": "United States",
    "city": "Scranton"
  },
  {
    "id": 187,
    "first_name": "Shaw",
    "last_name": "Hucke",
    "email": "shucke56@netlog.com",
    "gender": "Male",
    "university": "Ocean University of China",
    "country": "China",
    "city": "Chaoyang"
  },
  {
    "id": 188,
    "first_name": "Esra",
    "last_name": "Jamary",
    "email": "ejamary57@vimeo.com",
    "gender": "Agender",
    "university": "Universitas Andalas",
    "country": "Indonesia",
    "city": "Mondoteko"
  },
  {
    "id": 189,
    "first_name": "Kim",
    "last_name": "Oldroyd",
    "email": "koldroyd58@xinhuanet.com",
    "gender": "Female",
    "university": "Magnitogorsk State University",
    "country": "Russia",
    "city": "Novyy Karachay"
  },
  {
    "id": 190,
    "first_name": "Darrelle",
    "last_name": "Coenraets",
    "email": "dcoenraets59@blogspot.com",
    "gender": "Female",
    "university": "Universidade Federal do Maranhão",
    "country": "Brazil",
    "city": "Goiás"
  },
  {
    "id": 191,
    "first_name": "Margeaux",
    "last_name": "Laybourn",
    "email": "mlaybourn5a@canalblog.com",
    "gender": "Female",
    "university": "Institut Commercial de Nancy",
    "country": "France",
    "city": "Bourg-lès-Valence"
  },
  {
    "id": 192,
    "first_name": "Nata",
    "last_name": "Elfitt",
    "email": "nelfitt5b@state.gov",
    "gender": "Female",
    "university": "Dr. Panjabrao Deshmukh Krishi Vidyapeeth",
    "country": "Sint Maarten",
    "city": "Philipsburg"
  },
  {
    "id": 193,
    "first_name": "Aurore",
    "last_name": "Gallaher",
    "email": "agallaher5c@studiopress.com",
    "gender": "Female",
    "university": "Tajik National University",
    "country": "Tajikistan",
    "city": "Norak"
  },
  {
    "id": 194,
    "first_name": "Earvin",
    "last_name": "Brandin",
    "email": "ebrandin5d@livejournal.com",
    "gender": "Male",
    "university": "Universidad Católica Nuestra Senora de la Asunción",
    "country": "Paraguay",
    "city": "Naranjal"
  },
  {
    "id": 195,
    "first_name": "Kimberly",
    "last_name": "Holson",
    "email": "kholson5e@macromedia.com",
    "gender": "Female",
    "university": "Guangxi Normal University",
    "country": "China",
    "city": "Qiaotou"
  },
  {
    "id": 196,
    "first_name": "Brittani",
    "last_name": "Vickers",
    "email": "bvickers5f@creativecommons.org",
    "gender": "Female",
    "university": "Vytautas Magnus University",
    "country": "Lithuania",
    "city": "Pasvalys"
  },
  {
    "id": 197,
    "first_name": "Giff",
    "last_name": "Willoughby",
    "email": "gwilloughby5g@zdnet.com",
    "gender": "Male",
    "university": "Kazan State Academy of Architecture and Civil Engineering",
    "country": "Russia",
    "city": "Svetlograd"
  },
  {
    "id": 198,
    "first_name": "Evvie",
    "last_name": "Tarplee",
    "email": "etarplee5h@gizmodo.com",
    "gender": "Female",
    "university": "Mykolo Romerio university",
    "country": "Lithuania",
    "city": "Širvintos"
  },
  {
    "id": 199,
    "first_name": "Arnoldo",
    "last_name": "Taplow",
    "email": "ataplow5i@disqus.com",
    "gender": "Male",
    "university": "Ecole Nationale Supérieure de Chimie de Lille",
    "country": "France",
    "city": "Moulins"
  }
]
